CHANGELOG.txt
LICENSE.txt
MANIFEST.in
README.txt
setup.py
apotailib.egg-info/PKG-INFO
apotailib.egg-info/SOURCES.txt
apotailib.egg-info/dependency_links.txt
apotailib.egg-info/top_level.txt
calculator/__init__.py
calculator/easy_calculator.py