Metadata-Version: 2.1
Name: apotailib
Version: 0.0.2
Summary: A very basic calculator
Home-page: UNKNOWN
Author: Duy Nguyen
Author-email: duynguyenngoc@hotmail.com
License: MIT
Keywords: ai
Platform: UNKNOWN
Classifier: Development Status :: 5 - Production/Stable
Classifier: Intended Audience :: Education
Classifier: Operating System :: Microsoft :: Windows :: Windows 10
Classifier: License :: OSI Approved :: MIT License
Classifier: Programming Language :: Python :: 3.9
License-File: LICENSE.txt
